{
	"img": "~img/flymyrtlebeach.png",
	"startDate": 2019,
	"endDate": 2019,
	"title": "FlyMyrtleBeach.com Website and Integrations",
	"desc": "Myrtle Beach International Airport website was ailed with technical bugs and di culty of use, having been built on top of an outdated content management system written in an obscure, restrictive language. Worked as a designer and the main developer to create a completely new, responsive, and cross-browser website with WordPress, and custom plugins were developed speci cally for ease of use and integration with third party APIs, including A2 Analytics. Technologies used were WordPress, PHP, Node.js, and Adobe Illustrator."
}